LICENSE
kwonfig/__init__.py
kwonfig/constants.py
kwonfig/handlers/__init__.py
kwonfig/handlers/dhall.py
kwonfig/handlers/hjson.py
kwonfig/handlers/ini.py
kwonfig/handlers/json.py
kwonfig/handlers/json5.py
kwonfig/handlers/python.py
kwonfig/handlers/toml.py
kwonfig/handlers/yaml.py
kwonfig/plugin.py
kwonfig/utils/__init__.py
kwonfig/utils/lazy.py
kwonfig/utils/models.py
kwonfig/utils/types.py
kwonfig-0.3.1.dist-info/LICENSE
kwonfig-0.3.1.dist-info/METADATA
kwonfig-0.3.1.dist-info/WHEEL
kwonfig-0.3.1.dist-info/RECORD
