Metadata-Version: 2.1
Name: kwonfig
Version: 0.3.1
Summary: Complete, extensible configuration manager
Home-page: https://gitlab.kokakiwi.net/kokakiwi/kwonfig
License: BSD-3-Clause
Author: KokaKiwi
Author-email: kokakiwi+git@kokakiwi.net
Requires-Python: >=3.7,<4.0
Classifier: Development Status :: 4 - Beta
Classifier: Intended Audience :: Developers
Classifier: License :: OSI Approved :: BSD License
Classifier: Operating System :: OS Independent
Classifier: Programming Language :: Python
Classifier: Programming Language :: Python :: 3
Classifier: Programming Language :: Python :: 3.7
Classifier: Programming Language :: Python :: 3.8
Classifier: Programming Language :: Python :: 3.9
Classifier: Programming Language :: Python :: 3.10
Classifier: Programming Language :: Python :: 3.11
Classifier: Programming Language :: Python :: 3
Classifier: Programming Language :: Python :: 3 :: Only
Classifier: Programming Language :: Python :: 3.7
Classifier: Programming Language :: Python :: 3.8
Classifier: Programming Language :: Python :: 3.9
Classifier: Topic :: Software Development
Classifier: Topic :: Utilities
Classifier: Typing :: Typed
Provides-Extra: all
Provides-Extra: ini
Provides-Extra: toml
Provides-Extra: yaml
Requires-Dist: deepmerge (>=0.1,<0.2)
Requires-Dist: dhall (>=0.1,<0.2) ; extra == "all"
Requires-Dist: hjson (>=3.0,<4.0) ; extra == "all"
Requires-Dist: ini-parser (>=1.0,<2.0) ; extra == "all" or extra == "ini"
Requires-Dist: json5 (>=0.9,<0.10) ; extra == "all"
Requires-Dist: loguru (>=0.5,<0.6)
Requires-Dist: pluggy (>=1.0,<2.0)
Requires-Dist: pydantic (>=1.10,<2.0) ; extra == "all"
Requires-Dist: qtoml (>=0.3,<0.4) ; extra == "all" or extra == "toml"
Requires-Dist: rtoml (>=0.9,<0.10)
Requires-Dist: ruamel.yaml (>=0.16,<0.17) ; extra == "all" or extra == "yaml"
Project-URL: Issues, https://gitlab.kokakiwi.net/kokakiwi/kwonfig/-/issues
Project-URL: Repository, https://gitlab.kokakiwi.net/kokakiwi/kwonfig.git
